setup.py
bin/njuner
njuner/__init__.py
njuner/njuner.py
njuner/run.py
njuner.egg-info/PKG-INFO
njuner.egg-info/SOURCES.txt
njuner.egg-info/dependency_links.txt
njuner.egg-info/requires.txt
njuner.egg-info/top_level.txt
njuner/pytorch_pretrained_bert/__init__.py
njuner/pytorch_pretrained_bert/modeling.py
njuner/pytorch_pretrained_bert/tokenization.py