Metadata-Version: 1.2
Name: njuner
Version: 0.1.9
Summary: A NER tool from Nanjing University NLP Group.
Home-page: https://github.com/ericput/bert-ner
Author: Putong
Author-email: put@nlp.nju.edu.cn
License: MIT License
Platform: Linux
Requires-Python: >=3.5.0
